zope/i18nmessageid/__init__.py
zope/i18nmessageid/_zope_i18nmessageid_message.c
zope/i18nmessageid/_zope_i18nmessageid_message.cpython-311-darwin.so
zope/i18nmessageid/message.py
zope/i18nmessageid/tests.py
zope_i18nmessageid-8.2.dist-info/licenses/LICENSE.txt
zope_i18nmessageid-8.2.dist-info/METADATA
zope_i18nmessageid-8.2.dist-info/WHEEL
zope_i18nmessageid-8.2.dist-info/top_level.txt
zope_i18nmessageid-8.2.dist-info/RECORD
