Metadata-Version: 2.4
Name: zope.i18nmessageid
Version: 8.2
Summary: Message Identifiers for internationalization
Author-email: Zope Foundation and contributors <zope-dev@zope.dev>
Maintainer-email: Plone Foundation and contributors <zope-dev@zope.dev>
License-Expression: ZPL-2.1
Project-URL: Documentation, https://zopei18nmessageid.readthedocs.io
Project-URL: Issues, https://github.com/zopefoundation/zope.i18nmessageid/issues
Project-URL: Source, https://github.com/zopefoundation/zope.i18nmessageid
Project-URL: Changelog, https://github.com/zopefoundation/zope.i18nmessageid/blob/master/CHANGES.rst
Keywords: zope,i18n,message,factory
Classifier: Development Status :: 5 - Production/Stable
Classifier: Environment :: Web Environment
Classifier: Framework :: Zope :: 3
Classifier: Intended Audience :: Developers
Classifier: Operating System :: OS Independent
Classifier: Programming Language :: Python
Classifier: Programming Language :: Python :: 3
Classifier: Programming Language :: Python :: 3 :: Only
Classifier: Programming Language :: Python :: 3.10
Classifier: Programming Language :: Python :: 3.11
Classifier: Programming Language :: Python :: 3.12
Classifier: Programming Language :: Python :: 3.13
Classifier: Programming Language :: Python :: 3.14
Classifier: Programming Language :: Python :: Implementation :: CPython
Classifier: Programming Language :: Python :: Implementation :: PyPy
Classifier: Topic :: Internet :: WWW/HTTP
Requires-Python: >=3.10
License-File: LICENSE.txt
Requires-Dist: zope.interface
Provides-Extra: docs
Requires-Dist: Sphinx; extra == "docs"
Requires-Dist: furo; extra == "docs"
Provides-Extra: test
Requires-Dist: coverage; extra == "test"
Requires-Dist: zope.testrunner>=6.4; extra == "test"
Provides-Extra: testing
Requires-Dist: coverage; extra == "testing"
Requires-Dist: zope.testrunner>=6.4; extra == "testing"
Dynamic: license-file
